[{"data": {"id": "compartment", "label": "compartment"}, "group": "nodes", "classes": "compartment"}, {"data": {"id": "Normal_T_cells", "label": "Normal_T_cells", "parent": "compartment", "sboTerm": -1}, "group": "nodes", "classes": "species"}, {"data": {"id": "CAR_T_cells", "label": "CAR_T_cells", "parent": "compartment", "sboTerm": -1}, "group": "nodes", "classes": "species"}, {"data": {"id": "Antigen_presenting_tumour_cells", "label": "Antigen-presenting_tumour_cells", "parent": "compartment", "sboTerm": -1}, "group": "nodes", "classes": "species"}, {"data": {"id": "Total_lymphocyte_count", "label": "Total_lymphocyte_count", "parent": "compartment", "sboTerm": -1}, "group": "nodes", "classes": "species"}, {"data": {"id": "Normal_T_cell_population_growth_Normal_T_cells", "source": "Normal_T_cell_population_growth", "target": "Normal_T_cells"}, "group": "edges", "classes": "productEdge"}, {"data": {"id": "CAR_T_cells_Normal_T_cell_population_growth", "source": "CAR_T_cells", "target": "Normal_T_cell_population_growth", "sboTerm": -1}, "group": "edges", "classes": "modifierEdge"}, {"data": {"id": "Normal_T_cell_population_growth", "label": "Normal_T_cell_population_growth", "parent": "compartment", "width": 15, "height": 15}, "group": "nodes", "classes": "reaction"}, {"data": {"id": "CAR_T_cell_population_growth_CAR_T_cells", "source": "CAR_T_cell_population_growth", "target": "CAR_T_cells"}, "group": "edges", "classes": "productEdge"}, {"data": {"id": "Normal_T_cells_CAR_T_cell_population_growth", "source": "Normal_T_cells", "target": "CAR_T_cell_population_growth", "sboTerm": -1}, "group": "edges", "classes": "modifierEdge"}, {"data": {"id": "CAR_T_cell_population_growth", "label": "CAR_T_cell_population_growth", "parent": "compartment", "width": 15, "height": 15}, "group": "nodes", "classes": "reaction"}, {"data": {"id": "Tumour_growth_Antigen_presenting_tumour_cells", "source": "Tumour_growth", "target": "Antigen_presenting_tumour_cells"}, "group": "edges", "classes": "productEdge"}, {"data": {"id": "Tumour_growth", "label": "Tumour_growth", "parent": "compartment", "width": 15, "height": 15}, "group": "nodes", "classes": "reaction"}, {"data": {"id": "Antigen_presenting_tumour_cells_Tumour_killing", "source": "Antigen_presenting_tumour_cells", "target": "Tumour_killing"}, "group": "edges", "classes": "reactantEdge"}, {"data": {"id": "CAR_T_cells_Tumour_killing", "source": "CAR_T_cells", "target": "Tumour_killing", "sboTerm": -1}, "group": "edges", "classes": "modifierEdge"}, {"data": {"id": "Tumour_killing", "label": "Tumour_killing", "parent": "compartment", "width": 15, "height": 15}, "group": "nodes", "classes": "reaction"}]