[{"data": {"id": "gut", "label": ""}, "group": "nodes", "classes": "compartment"}, {"data": {"id": "Vdopa", "label": "V_L_Dopa"}, "group": "nodes", "classes": "compartment"}, {"data": {"id": "V_3_OMD", "label": ""}, "group": "nodes", "classes": "compartment"}, {"data": {"id": "V1_B", "label": ""}, "group": "nodes", "classes": "compartment"}, {"data": {"id": "V2_B", "label": ""}, "group": "nodes", "classes": "compartment"}, {"data": {"id": "V1_M", "label": ""}, "group": "nodes", "classes": "compartment"}, {"data": {"id": "V2_M", "label": ""}, "group": "nodes", "classes": "compartment"}, {"data": {"id": "A_dopa", "label": "", "parent": "gut", "sboTerm": 247}, "group": "nodes", "classes": "species"}, {"data": {"id": "A_B", "label": "", "parent": "gut", "sboTerm": 247}, "group": "nodes", "classes": "species"}, {"data": {"id": "A_M", "label": "", "parent": "gut", "sboTerm": 247}, "group": "nodes", "classes": "species"}, {"data": {"id": "C_dopa", "label": "", "parent": "Vdopa", "sboTerm": 247}, "group": "nodes", "classes": "species"}, {"data": {"id": "C_OMD", "label": "C_3-OMD", "parent": "V_3_OMD", "sboTerm": 247}, "group": "nodes", "classes": "species"}, {"data": {"id": "C1_M", "label": "", "parent": "V1_M", "sboTerm": 247}, "group": "nodes", "classes": "species"}, {"data": {"id": "C2_M", "label": "", "parent": "V2_M", "sboTerm": 247}, "group": "nodes", "classes": "species"}, {"data": {"id": "C1_B", "label": "", "parent": "V1_B", "sboTerm": 247}, "group": "nodes", "classes": "species"}, {"data": {"id": "C2_B", "label": "", "parent": "V2_B", "sboTerm": 247}, "group": "nodes", "classes": "species"}, {"data": {"id": "A_dopa_l_dopa_absorption", "source": "A_dopa", "target": "l_dopa_absorption"}, "group": "edges", "classes": "reactantEdge"}, {"data": {"id": "l_dopa_absorption_C_dopa", "source": "l_dopa_absorption", "target": "C_dopa"}, "group": "edges", "classes": "productEdge"}, {"data": {"id": "l_dopa_absorption", "label": "L_Dopa absorption from gut", "parent": "gut", "width": 15, "height": 15}, "group": "nodes", "classes": "reaction"}, {"data": {"id": "A_dopa_l_dopa_blood_hepa_clearance", "source": "A_dopa", "target": "l_dopa_blood_hepa_clearance"}, "group": "edges", "classes": "reactantEdge"}, {"data": {"id": "l_dopa_blood_hepa_clearance", "label": "hepatic and blood L-Dopa clearance", "parent": "gut", "width": 15, "height": 15}, "group": "nodes", "classes": "reaction"}, {"data": {"id": "A_M_ro_04_5127_absorption", "source": "A_M", "target": "ro_04_5127_absorption"}, "group": "edges", "classes": "reactantEdge"}, {"data": {"id": "ro_04_5127_absorption_C1_M", "source": "ro_04_5127_absorption", "target": "C1_M"}, "group": "edges", "classes": "productEdge"}, {"data": {"id": "ro_04_5127_absorption", "label": "ro 04-5127 absorption from gut", "parent": "gut", "width": 15, "height": 15}, "group": "nodes", "classes": "reaction"}, {"data": {"id": "A_B_benserazide_absorption", "source": "A_B", "target": "benserazide_absorption"}, "group": "edges", "classes": "reactantEdge"}, {"data": {"id": "benserazide_absorption_C1_B", "source": "benserazide_absorption", "target": "C1_B"}, "group": "edges", "classes": "productEdge"}, {"data": {"id": "benserazide_absorption", "label": "benserazide absorption from gut", "parent": "gut", "width": 15, "height": 15}, "group": "nodes", "classes": "reaction"}, {"data": {"id": "A_B_benserazide_gut_clearance", "source": "A_B", "target": "benserazide_gut_clearance"}, "group": "edges", "classes": "reactantEdge"}, {"data": {"id": "benserazide_gut_clearance", "label": "benserazide clearance from gut", "parent": "gut", "width": 15, "height": 15}, "group": "nodes", "classes": "reaction"}, {"data": {"id": "C_dopa_AADC_clearance", "source": "C_dopa", "target": "AADC_clearance"}, "group": "edges", "classes": "reactantEdge"}, {"data": {"id": "AADC_clearance", "label": "L-Dopa clearance via AADC ", "parent": "Vdopa", "width": 15, "height": 15}, "group": "nodes", "classes": "reaction"}, {"data": {"id": "C_dopa_COMT_clearance", "source": "C_dopa", "target": "COMT_clearance"}, "group": "edges", "classes": "reactantEdge"}, {"data": {"id": "COMT_clearance_C_OMD", "source": "COMT_clearance", "target": "C_OMD"}, "group": "edges", "classes": "productEdge"}, {"data": {"id": "COMT_clearance", "label": "L-Dopa clearance via COMT", "parent": "Vdopa", "width": 15, "height": 15}, "group": "nodes", "classes": "reaction"}, {"data": {"id": "C_dopa_rest_clearance", "source": "C_dopa", "target": "rest_clearance"}, "group": "edges", "classes": "reactantEdge"}, {"data": {"id": "rest_clearance", "label": "rest clearance of L-Dopa", "parent": "Vdopa", "width": 15, "height": 15}, "group": "nodes", "classes": "reaction"}, {"data": {"id": "C_OMD__3_OMD_clearance", "source": "C_OMD", "target": "_3_OMD_clearance"}, "group": "edges", "classes": "reactantEdge"}, {"data": {"id": "_3_OMD_clearance", "label": "3-OMD clearance", "parent": "V_3_OMD", "width": 15, "height": 15}, "group": "nodes", "classes": "reaction"}, {"data": {"id": "C1_B_bens_clearance", "source": "C1_B", "target": "bens_clearance"}, "group": "edges", "classes": "reactantEdge"}, {"data": {"id": "bens_clearance", "label": "benserazide clearance", "parent": "V1_B", "width": 15, "height": 15}, "group": "nodes", "classes": "reaction"}, {"data": {"id": "C1_B_bens_metabolism", "source": "C1_B", "target": "bens_metabolism"}, "group": "edges", "classes": "reactantEdge"}, {"data": {"id": "bens_metabolism_C1_M", "source": "bens_metabolism", "target": "C1_M"}, "group": "edges", "classes": "productEdge"}, {"data": {"id": "bens_metabolism", "label": "benserazide metabolism to ro 04-5127", "parent": "V1_B", "width": 15, "height": 15}, "group": "nodes", "classes": "reaction"}, {"data": {"id": "C1_M_ro_clearance", "source": "C1_M", "target": "ro_clearance"}, "group": "edges", "classes": "reactantEdge"}, {"data": {"id": "ro_clearance", "label": "ro 04-5127 clearance", "parent": "V1_M", "width": 15, "height": 15}, "group": "nodes", "classes": "reaction"}, {"data": {"id": "C1_B_bens_distribution", "source": "C1_B", "target": "bens_distribution"}, "group": "edges", "classes": "reactantEdge"}, {"data": {"id": "bens_distribution_C2_B", "source": "bens_distribution", "target": "C2_B"}, "group": "edges", "classes": "productEdge"}, {"data": {"id": "bens_distribution", "label": "benserazide distribution", "parent": "V1_B", "width": 15, "height": 15}, "group": "nodes", "classes": "reaction"}, {"data": {"id": "C1_M_ro_distribution", "source": "C1_M", "target": "ro_distribution"}, "group": "edges", "classes": "reactantEdge"}, {"data": {"id": "ro_distribution_C2_M", "source": "ro_distribution", "target": "C2_M"}, "group": "edges", "classes": "productEdge"}, {"data": {"id": "ro_distribution", "label": "ro 04-5127 distribution", "parent": "V1_M", "width": 15, "height": 15}, "group": "nodes", "classes": "reaction"}]