[{"data": {"id": "Cytoplasm", "label": "cytoplasm"}, "group": "nodes", "classes": "compartment"}, {"data": {"id": "ER", "label": "endoplasmic reticulum"}, "group": "nodes", "classes": "compartment"}, {"data": {"id": "Ca_cyt", "label": "Cytosolic Calcium", "parent": "Cytoplasm", "sboTerm": -1}, "group": "nodes", "classes": "species"}, {"data": {"id": "Ca_er", "label": "ER Calcium", "parent": "ER", "sboTerm": -1}, "group": "nodes", "classes": "species"}, {"data": {"id": "IP3_cyt", "label": "Cytosolic IP3", "parent": "Cytoplasm", "sboTerm": -1}, "group": "nodes", "classes": "species"}, {"data": {"id": "Na_cyt", "label": "Cytosolic Sodium", "parent": "Cytoplasm", "sboTerm": -1}, "group": "nodes", "classes": "species"}, {"data": {"id": "ATP_cyt", "label": "Cytosolic ATP", "parent": "Cytoplasm", "sboTerm": -1}, "group": "nodes", "classes": "species"}, {"data": {"id": "ADP_cyt", "label": "Cytosolic ADP", "parent": "Cytoplasm", "sboTerm": -1}, "group": "nodes", "classes": "species"}, {"data": {"id": "Calcium_cyt_Ivca_Ca_cyt", "source": "Calcium_cyt_Ivca", "target": "Ca_cyt"}, "group": "edges", "classes": "productEdge"}, {"data": {"id": "Calcium_cyt_Ivca", "label": "", "parent": "Cytoplasm", "width": 15, "height": 15}, "group": "nodes", "classes": "reaction"}, {"data": {"id": "Calcium_cyt_Inaca_Ca_cyt", "source": "Calcium_cyt_Inaca", "target": "Ca_cyt"}, "group": "edges", "classes": "productEdge"}, {"data": {"id": "Calcium_cyt_Inaca", "label": "", "parent": "Cytoplasm", "width": 15, "height": 15}, "group": "nodes", "classes": "reaction"}, {"data": {"id": "Ca_cyt_Calcium_cyt_Icapump", "source": "Ca_cyt", "target": "Calcium_cyt_Icapump"}, "group": "edges", "classes": "reactantEdge"}, {"data": {"id": "Calcium_cyt_Icapump", "label": "", "parent": "Cytoplasm", "width": 15, "height": 15}, "group": "nodes", "classes": "reaction"}, {"data": {"id": "Ca_cyt_Calcium_cyt_Jerp", "source": "Ca_cyt", "target": "Calcium_cyt_Jerp"}, "group": "edges", "classes": "reactantEdge"}, {"data": {"id": "Calcium_cyt_Jerp_Ca_er", "source": "Calcium_cyt_Jerp", "target": "Ca_er"}, "group": "edges", "classes": "productEdge"}, {"data": {"id": "Calcium_cyt_Jerp", "label": "", "parent": "Cytoplasm", "width": 15, "height": 15}, "group": "nodes", "classes": "reaction"}, {"data": {"id": "Ca_er_Calcium_cyt_Jout", "source": "Ca_er", "target": "Calcium_cyt_Jout"}, "group": "edges", "classes": "reactantEdge"}, {"data": {"id": "Calcium_cyt_Jout_Ca_cyt", "source": "Calcium_cyt_Jout", "target": "Ca_cyt"}, "group": "edges", "classes": "productEdge"}, {"data": {"id": "Calcium_cyt_Jout", "label": "", "parent": "ER", "width": 15, "height": 15}, "group": "nodes", "classes": "reaction"}, {"data": {"id": "Ca_cyt_Calcium_cyt_sequestration", "source": "Ca_cyt", "target": "Calcium_cyt_sequestration"}, "group": "edges", "classes": "reactantEdge"}, {"data": {"id": "Calcium_cyt_sequestration", "label": "", "parent": "Cytoplasm", "width": 15, "height": 15}, "group": "nodes", "classes": "reaction"}, {"data": {"id": "IP3_synthesis_IP3_cyt", "source": "IP3_synthesis", "target": "IP3_cyt"}, "group": "edges", "classes": "productEdge"}, {"data": {"id": "Ca_cyt_IP3_synthesis", "source": "Ca_cyt", "target": "IP3_synthesis", "sboTerm": -1}, "group": "edges", "classes": "modifierEdge"}, {"data": {"id": "IP3_synthesis", "label": "", "parent": "Cytoplasm", "width": 15, "height": 15}, "group": "nodes", "classes": "reaction"}, {"data": {"id": "IP3_cyt_IP3_degradation", "source": "IP3_cyt", "target": "IP3_degradation"}, "group": "edges", "classes": "reactantEdge"}, {"data": {"id": "IP3_degradation", "label": "", "parent": "Cytoplasm", "width": 15, "height": 15}, "group": "nodes", "classes": "reaction"}, {"data": {"id": "Na_cyt_Na_Inaca", "source": "Na_cyt", "target": "Na_Inaca"}, "group": "edges", "classes": "reactantEdge"}, {"data": {"id": "Na_Inaca", "label": "", "parent": "Cytoplasm", "width": 15, "height": 15}, "group": "nodes", "classes": "reaction"}, {"data": {"id": "Na_cyt_Na_Inak", "source": "Na_cyt", "target": "Na_Inak"}, "group": "edges", "classes": "reactantEdge"}, {"data": {"id": "Na_Inak", "label": "", "parent": "Cytoplasm", "width": 15, "height": 15}, "group": "nodes", "classes": "reaction"}, {"data": {"id": "Na_Ina_Na_cyt", "source": "Na_Ina", "target": "Na_cyt"}, "group": "edges", "classes": "productEdge"}, {"data": {"id": "Na_Ina", "label": "", "parent": "Cytoplasm", "width": 15, "height": 15}, "group": "nodes", "classes": "reaction"}, {"data": {"id": "Na_Icran_Na_cyt", "source": "Na_Icran", "target": "Na_cyt"}, "group": "edges", "classes": "productEdge"}, {"data": {"id": "Na_Icran", "label": "", "parent": "Cytoplasm", "width": 15, "height": 15}, "group": "nodes", "classes": "reaction"}, {"data": {"id": "ATP_production_ATP_cyt", "source": "ATP_production", "target": "ATP_cyt"}, "group": "edges", "classes": "productEdge"}, {"data": {"id": "ADP_cyt_ATP_production", "source": "ADP_cyt", "target": "ATP_production", "sboTerm": -1}, "group": "edges", "classes": "modifierEdge"}, {"data": {"id": "ATP_production", "label": "", "parent": "Cytoplasm", "width": 15, "height": 15}, "group": "nodes", "classes": "reaction"}, {"data": {"id": "ATP_cyt_ATP_NaKATPase", "source": "ATP_cyt", "target": "ATP_NaKATPase"}, "group": "edges", "classes": "reactantEdge"}, {"data": {"id": "ATP_NaKATPase", "label": "", "parent": "Cytoplasm", "width": 15, "height": 15}, "group": "nodes", "classes": "reaction"}, {"data": {"id": "ATP_cyt_ATP_Capump", "source": "ATP_cyt", "target": "ATP_Capump"}, "group": "edges", "classes": "reactantEdge"}, {"data": {"id": "ATP_Capump", "label": "", "parent": "Cytoplasm", "width": 15, "height": 15}, "group": "nodes", "classes": "reaction"}, {"data": {"id": "ATP_cyt_ATP_Jerp", "source": "ATP_cyt", "target": "ATP_Jerp"}, "group": "edges", "classes": "reactantEdge"}, {"data": {"id": "ATP_Jerp", "label": "", "parent": "Cytoplasm", "width": 15, "height": 15}, "group": "nodes", "classes": "reaction"}, {"data": {"id": "ATP_cyt_ATP_Ca_dependent_consumption", "source": "ATP_cyt", "target": "ATP_Ca_dependent_consumption"}, "group": "edges", "classes": "reactantEdge"}, {"data": {"id": "Ca_cyt_ATP_Ca_dependent_consumption", "source": "Ca_cyt", "target": "ATP_Ca_dependent_consumption", "sboTerm": -1}, "group": "edges", "classes": "modifierEdge"}, {"data": {"id": "ATP_Ca_dependent_consumption", "label": "", "parent": "Cytoplasm", "width": 15, "height": 15}, "group": "nodes", "classes": "reaction"}, {"data": {"id": "ATP_cyt_ATP_consumption", "source": "ATP_cyt", "target": "ATP_consumption"}, "group": "edges", "classes": "reactantEdge"}, {"data": {"id": "ATP_consumption", "label": "", "parent": "Cytoplasm", "width": 15, "height": 15}, "group": "nodes", "classes": "reaction"}]